extractor/__init__.py
extractor/_version.py
extractor/exceptions.py
extractor/stream.py
extractor/tools.py
extractor/formats/__init__.py
extractor/formats/opentype.py
extractor/formats/ttx.py
extractor/formats/type1.py
extractor/formats/vfb.py
extractor/formats/woff.py
ufo_extractor-0.8.1.dist-info/License.txt
ufo_extractor-0.8.1.dist-info/METADATA
ufo_extractor-0.8.1.dist-info/WHEEL
ufo_extractor-0.8.1.dist-info/entry_points.txt
ufo_extractor-0.8.1.dist-info/top_level.txt
ufo_extractor-0.8.1.dist-info/zip-safe
ufo_extractor-0.8.1.dist-info/RECORD
