Metadata-Version: 2.1
Name: ufo_extractor
Version: 0.8.1
Summary: Tools for extracting data from font binaries into UFO objects.
Home-page: https://github.com/robotools/extractor
Author: Tal Leming
Author-email: tal@typesupply.com
Maintainer: Just van Rossum, Frederik Berlaen, Ben Kiel
Maintainer-email: justvanrossum@gmail.com
License: MIT
Classifier: Development Status :: 4 - Beta
Classifier: Environment :: Console
Classifier: Environment :: Other Environment
Classifier: Intended Audience :: Developers
Classifier: License :: OSI Approved :: MIT License
Classifier: Natural Language :: English
Classifier: Operating System :: OS Independent
Classifier: Programming Language :: Python :: 3
Classifier: Programming Language :: Python
Classifier: Topic :: Multimedia :: Graphics :: Editors :: Vector-Based
Classifier: Topic :: Multimedia :: Graphics :: Graphics Conversion
Classifier: Topic :: Multimedia :: Graphics
Classifier: Topic :: Software Development :: Libraries :: Python Modules
Classifier: Topic :: Text Processing :: Fonts
Requires-Python: >=3.8
License-File: License.txt
Requires-Dist: fonttools[lxml,type1,ufo,unicode,woff]>=4.17.0
Requires-Dist: fontFeatures
Provides-Extra: script
Requires-Dist: ufoLib2; extra == "script"
Provides-Extra: vfb
Requires-Dist: vfbLib>=0.7.1; extra == "vfb"
